scapr/__init__.py
scapr/__main__.py
scapr/scap.py
scapr-2025.12.2.dist-info/entry_points.txt
scapr-2025.12.2.dist-info/licenses/LICENSE
scapr-2025.12.2.dist-info/WHEEL
scapr-2025.12.2.dist-info/METADATA
scapr-2025.12.2.dist-info/RECORD
