Metadata-Version: 2.4
Name: scapr
Version: 2025.12.2
Summary: A Python script that uses Pillow's ImageGrab to capture screenshots.
Keywords: image,screen capture,screen shot,screenshot
Author-email: Bill Melvin <bill@billmelvin.com>
Requires-Python: >=3.10
Classifier: License :: OSI Approved :: MIT License
License-File: LICENSE
Requires-Dist: pillow
Requires-Dist: rich
Requires-Dist: pytest ; extra == "test"
Project-URL: Repository, https://github.com/wmelvin/scapr
Provides-Extra: test
